adaptive_kmpc_py/__init__.py
adaptive_kmpc_py/controller.py
adaptive_kmpc_py/predictor.py
adaptive_kmpc_py-0.1.1.dist-info/LICENSE
adaptive_kmpc_py-0.1.1.dist-info/METADATA
adaptive_kmpc_py-0.1.1.dist-info/WHEEL
adaptive_kmpc_py-0.1.1.dist-info/RECORD
