Metadata-Version: 2.3
Name: adaptive-kmpc-py
Version: 0.1.1
Summary: A Python implementation of the adaptive Koopman model predictive control algorithm
License: MIT
Author: Adriano del Río
Requires-Python: >=3.10,<3.13
Classifier: License :: OSI Approved :: MIT License
Classifier: Programming Language :: Python :: 3
Classifier: Programming Language :: Python :: 3.10
Classifier: Programming Language :: Python :: 3.11
Classifier: Programming Language :: Python :: 3.12
Requires-Dist: numba (>=0.58.0,<0.61.0)
Requires-Dist: numpy (>=1.22.4,<1.26.0)
Requires-Dist: osqp (>=0.6.2,<1.1.0)
Requires-Dist: pykoopman (==1.1.0)
Requires-Dist: scipy (>=1.9.0,<=1.11.2)
